{
    "hyperparameters": {
        "objective": "reg:squarederror",
        "base_score": null,
        "booster": null,
        "callbacks": null,
        "colsample_bylevel": null,
        "colsample_bynode": null,
        "colsample_bytree": 1.0,
        "device": null,
        "early_stopping_rounds": null,
        "enable_categorical": true,
        "eval_metric": null,
        "feature_types": null,
        "feature_weights": null,
        "gamma": null,
        "grow_policy": null,
        "importance_type": null,
        "interaction_constraints": null,
        "learning_rate": 0.05,
        "max_bin": null,
        "max_cat_threshold": null,
        "max_cat_to_onehot": null,
        "max_delta_step": null,
        "max_depth": 6,
        "max_leaves": null,
        "min_child_weight": 1,
        "missing": null,
        "monotone_constraints": null,
        "multi_strategy": null,
        "n_estimators": 500,
        "n_jobs": null,
        "num_parallel_tree": null,
        "random_state": 42,
        "reg_alpha": null,
        "reg_lambda": null,
        "sampling_method": null,
        "scale_pos_weight": null,
        "subsample": 0.8,
        "tree_method": null,
        "validate_parameters": null,
        "verbosity": null
    },
    "performance_metrics": {
        "MAE": 6.64068,
        "MAPE": 0.09733,
        "RMSE": 8.64142,
        "R2": 0.85862
    },
    "feature_importance": [
        {
            "Feature": "zone_population",
            "Importance": 0.4774583578109741
        },
        {
            "Feature": "current_fill_percentage",
            "Importance": 0.19493432343006134
        },
        {
            "Feature": "event_urgency_score",
            "Importance": 0.09146352112293243
        },
        {
            "Feature": "is_holiday",
            "Importance": 0.08372573554515839
        },
        {
            "Feature": "kecamatan",
            "Importance": 0.07287609577178955
        },
        {
            "Feature": "day_of_week",
            "Importance": 0.037026576697826385
        },
        {
            "Feature": "daily_growth_rate",
            "Importance": 0.013362795114517212
        },
        {
            "Feature": "rainfall_today",
            "Importance": 0.00831830594688654
        },
        {
            "Feature": "tps_capacity_kg",
            "Importance": 0.007419232744723558
        },
        {
            "Feature": "tps_id",
            "Importance": 0.00676505034789443
        },
        {
            "Feature": "tps_type",
            "Importance": 0.006649943068623543
        },
        {
            "Feature": "is_weekend",
            "Importance": 0.0
        }
    ]
}